dsmtools/__init__.py
dsmtools/title_page.md
dsmtools/modeling/AE.py
dsmtools/modeling/AE_1282_SEU.h5
dsmtools/modeling/HAN.py
dsmtools/modeling/HAN_1282_SEU.h5
dsmtools/modeling/__init__.py
dsmtools/modeling/data_prep.py
dsmtools/modeling/model_abstract.py
dsmtools/modeling/modeling_guide.md
dsmtools/modeling/w2v_model_6dim_from_1200_seu.model
dsmtools/preprocessing/__init__.py
dsmtools/preprocessing/neuron_tree.py
dsmtools/preprocessing/preprocessing_guide.md
dsmtools/preprocessing/sequencing.py
dsmtools/preprocessing/swc_qc.py
dsmtools/utils/__init__.py
dsmtools/utils/misc.py
dsmtools/utils/swc.py
dsmtools/utils/ccf_atlas/__init__.py
dsmtools/utils/ccf_atlas/_annotation.py
dsmtools/utils/ccf_atlas/_image.py
dsmtools/utils/ccf_atlas/annotation_25.nrrd
dsmtools/utils/ccf_atlas/bs_level.csv
dsmtools/utils/ccf_atlas/dict_to_selected.json
DSM_tools-1.1.0.dist-info/LICENSE
DSM_tools-1.1.0.dist-info/METADATA
DSM_tools-1.1.0.dist-info/WHEEL
DSM_tools-1.1.0.dist-info/top_level.txt
DSM_tools-1.1.0.dist-info/RECORD
