Metadata-Version: 2.1
Name: DSM-tools
Version: 1.1.0
Summary: A python package for DSM utilities, which make seuences out of neuron SWC and use deep learning models to encode neurons and predict their types.
Author: Feng Xiong
Author-email: Zuo-Han Zhao <zzhmark@126.com>
License: MIT License
Project-URL: GitHub Project, https://github.com/xiongfengNJ/DSM-tools
Project-URL: Exhibition & Online Tools, http://101.43.104.173:8501
Project-URL: Data Server, http://101.43.104.173:8500/
Project-URL: Experiment Code, https://github.com/xiongfengNJ/neuron2seq
Keywords: neuron,morphology,HAN,autoencoder
Classifier: Programming Language :: Python :: 3
Classifier: License :: OSI Approved :: MIT License
Classifier: Operating System :: OS Independent
Requires-Python: >=3.9
License-File: LICENSE
Requires-Dist: tensorflow
Requires-Dist: pandas
Requires-Dist: scikit-learn
Requires-Dist: importlib-resources
Requires-Dist: gensim
Requires-Dist: SimpleITK
Requires-Dist: matplotlib
Provides-Extra: docs
Requires-Dist: pdoc ; extra == 'docs'
Provides-Extra: test
Requires-Dist: pytest ; extra == 'test'
Requires-Dist: pytest-xdist ; extra == 'test'
